randomplayground/__init__.py
randomplayground/randomplayground.py
randomplayground-0.0.5.dist-info/LICENSE
randomplayground-0.0.5.dist-info/METADATA
randomplayground-0.0.5.dist-info/WHEEL
randomplayground-0.0.5.dist-info/top_level.txt
randomplayground-0.0.5.dist-info/RECORD
