Metadata-Version: 2.1
Name: randomplayground
Version: 0.0.5
Summary: A package to help with random generator methods
Home-page: https://github.com/RandomPlayGround/random-play-ground
Author: @PyOctoCat
Author-email: davidinco@gmail.com
License: UNKNOWN
Platform: UNKNOWN
Classifier: Programming Language :: Python :: 3.7
Classifier: License :: OSI Approved :: GNU General Public License v3 (GPLv3)
Requires-Dist: Faker (>=4)
Requires-Dist: StringGenerator (>=0)
Requires-Dist: termcolor (>=1)
